spice/__init__.py
spice/call_args.py
spice/errors.py
spice/models.py
spice/providers.py
spice/spice.py
spice/spice_message.py
spice/utils.py
spice/wrapped_clients.py
spice/retry_strategy/__init__.py
spice/retry_strategy/converter_strategy.py
spice/retry_strategy/default_strategy.py
spice/retry_strategy/validator_strategy.py
spiceai-0.4.5.dist-info/METADATA
spiceai-0.4.5.dist-info/WHEEL
spiceai-0.4.5.dist-info/licenses/LICENSE
spiceai-0.4.5.dist-info/RECORD
