Metadata-Version: 2.3
Name: spiceai
Version: 0.4.5
Summary: A Python library for building AI-powered applications.
License: Apache-2.0
License-File: LICENSE
Requires-Dist: anthropic
Requires-Dist: httpx
Requires-Dist: jinja2
Requires-Dist: openai==1.35.3
Requires-Dist: pillow
Requires-Dist: python-dotenv
Requires-Dist: termcolor
Requires-Dist: tiktoken
Provides-Extra: dev
Requires-Dist: pyright; extra == 'dev'
Requires-Dist: pytest; extra == 'dev'
Requires-Dist: pytest-asyncio; extra == 'dev'
Requires-Dist: ruff; extra == 'dev'
